{
  "competition_name": "playground-series-s5e11",
  "kaggle_url": "https://www.kaggle.com/competitions/playground-series-s5e11",
  "api_output": "ref                                                          deadline             category    reward  teamCount  userHasEntered  \n-----------------------------------------------------------  -------------------  ----------  ------  ---------  --------------  \nhttps://www.kaggle.com/competitions/playground-series-s5e11  2025-11-30 23:59:00  Playground    Swag       1516           False  \n",
  "dataset_files": "name                         size  creationDate                \n---------------------  ----------  --------------------------  \nsample_submission.csv     2291139  2025-10-28 23:08:42.675000  \ntest.csv                 23021430  2025-10-28 23:08:43.494000  \ntrain.csv                55988519  2025-10-28 23:08:44.860000  \n",
  "collected_at": "2025-11-11 15:55:43",
  "dataset_downloaded": false,
  "notebook_count": 94,
  "notebook_authors": [
    "samithsachidanandan",
    "labibshahriar",
    "realvisheshbhardawaj",
    "amirmohamadrezaie",
    "yusufsertkayaysk",
    "mpwolke",
    "imaadmahmood",
    "sidakou",
    "jiaoyouzhang",
    "yekenot",
    "deepak915",
    "samarpanrai",
    "nina2025",
    "vishnupriyagarige",
    "masayakawamata",
    "astitwaagarwal",
    "pythoxb",
    "chikonzeroselemani",
    "adilshamim8",
    "rattans",
    "mariusborel",
    "ankitsharma224589",
    "kaibaur",
    "alekseyheleskul",
    "yousefelshahat2",
    "yigk4out",
    "sanjidh090",
    "visha1dubey",
    "rv1922",
    "thuandao",
    "shivams811",
    "hadesgo",
    "yeoyunsianggeremie",
    "jekiwantaufik",
    "berkayzkan",
    "shreyashpatil217",
    "mhamza0810",
    "onodera",
    "canozensoy",
    "ehsanesmaeili",
    "jockeroika",
    "tomasa2",
    "momerer",
    "rohansardar",
    "sharmajicoder",
    "sagarnagpure1310",
    "ufukckose",
    "mikhailnaumov",
    "karltonkxb",
    "arraylist1402",
    "subarnasaikia",
    "anthonytherrien",
    "tsunamazda",
    "skovalenko",
    "jocelyndumlao",
    "satyaprakashshukl",
    "ravi20076",
    "paharpurailab",
    "chitradas",
    "analyticaobscura",
    "abdmental01",
    "atharvagaikwad7143",
    "i0nlyaziz",
    "harshgupta4444"
  ]
}