{
  "original_path": "notebooks/store-sales-time-series-forecasting/hardikgarg03__store-sales/store-sales.ipynb",
  "quality_score": 43.044399999999996,
  "grade": "C",
  "techniques": {
    "feature_engineering": [
      "aggregation",
      "time_features",
      "lag_features"
    ],
    "eda": [
      "statistics",
      "visualization"
    ],
    "advanced_ml": [
      "lightgbm"
    ]
  },
  "libraries": [
    "pandas",
    "numpy",
    "sklearn",
    "lightgbm",
    "matplotlib",
    "seaborn"
  ],
  "category": "eda_fe",
  "competition": "store-sales-time-series-forecasting"
}